setbert/__init__.py
setbert/datamodules.py
setbert/datasets.py
setbert/metrics.py
setbert/models.py
setbert/utils.py
dbtk_setbert-1.0.2.dist-info/METADATA
dbtk_setbert-1.0.2.dist-info/WHEEL
dbtk_setbert-1.0.2.dist-info/top_level.txt
dbtk_setbert-1.0.2.dist-info/RECORD
