Metadata-Version: 2.4
Name: dbtk-setbert
Version: 1.0.2
Summary: The official SetBERT implementation using the deepbio-toolkit.
Author-email: "David W. Ludwig II" <davidludwigii@gmail.com>
Project-URL: Homepage, https://github.com/DLii-Research/setbert
Project-URL: Bug Tracker, https://github.com/DLii-Research/setbert/issues
Requires-Python: >=3.8
Requires-Dist: deepbio-toolkit>=0.4.2
Requires-Dist: dbtk-dnabert>=1.2.2
